{
	"version": 2018050301,
	"schedules": [
		{
			"version": 2017041700,
			"url": "https://luga-ev.github.io/frab-extras/2017/de/lit2017/public/schedule.xml",
			"title": "Augsburger Linux-Infotag 2017 (fixed)",
			"start": "2017-04-22",
			"end": "2017-04-22",
			"metadata": {
				"icon": "https://luga-ev.github.io/frab-extras/Tux2.png",
				"links": [
					{
						"url": "https://www.luga.de/Aktionen/LIT-2017/",
						"title": "Website"
					}
				]
			}
		},
		{
			"start": "2017-03-25",
			"end": "2017-03-26",
			"version": 2017031902,
			"url": "https://libreplanet.org/2017/lp2017-schedule.ics",
			"title": "LibrePlanet 2017",
			"metadata": {
				"links": [
					{
						"url": "https://libreplanet.org/2017/",
						"title": "Website"
					}
				]
			}
		},
		{
			"version": 2017040400,
			"url": "https://www.opensouthcode.org/conferences/opensouthcode2017/schedule.xml",
			"title": "Opensouthcode 2017",
			"start": "2017-05-05",
			"end": "2017-05-06",
			"metadata": {
				"links": [
					{
						"url": "https://www.opensouthcode.org/",
						"title": "Website"
					}
				],
				"icon": "https://www.opensouthcode.org/logo.png"
			}
		},
		{
			"version": 2017062300,
			"url": "http://www.tuebix.org/2017/giggity.xml",
			"title": "TUEBIX 2017",
			"start": "2017-06-24",
			"end": "2017-06-24",
			"metadata": {
				"icon": "http://www.tuebix.org/2017/giggity.icon.png",
				"links": [
					{
						"url": "http://www.tuebix.org/",
						"title": "Website"
					},
					{
						"url": "http://www.tuebix.org/anfahrt/",
						"title": "Anfahrt"
					}
				]
			}
		},
		{
			"version": 2017080500,
			"url": "https://program.sha2017.org/schedule.xml",
			"title": "SHA2017",
			"start": "2017-08-04",
			"end": "2017-08-08",
			"metadata": {
				"links": [
					{
						"url": "https://sha2017.org/",
						"title": "Website"
					},
					{
						"url": "https://map.sha2017.org/",
						"title": "Map"
					},
					{
						"url": "https://volunteer.sha2017.org/",
						"title": "Angels"
					},
					{
						"url": "https://wiki.sha2017.org/w/Main_Page",
						"title": "Wiki"
					}
				]
			}
		},
		{
			"title": "GUADEC 2017",
			"metadata": {
				"icon": "https://static.gnome.org/guadec-2017/icon1.png",
				"links": [
					{
						"url": "https://www.guadec.org/",
						"title": "Website"
					}
				]
			},
			"url": "https://static.gnome.org/guadec-2017/schedule.xml",
			"start": "2017-07-28",
			"end": "2017-07-30",
			"version": 2017071200
		},
		{
			"version": 2017072400,
			"url": "https://debconf17.debconf.org/schedule/pentabarf.xml",
			"title": "DebConf17",
			"start": "2017-08-05",
			"end": "2017-08-12",
			"metadata": {
				"icon": "https://debconf17.debconf.org/static/img/favicon/favicon-180.ea5f30d24599.png",
				"links": [
					{
						"url": "https://debconf17.debconf.org/",
						"title": "Website"
					},
					{
						"url": "https://wiki.debconf.org/wiki/DebConf17",
						"title": "Wiki"
					},
					{
						"url": "https://wiki.debconf.org/upload/8/88/DebConf17_venue_layout.png",
						"title": "Map",
						"type": "image/png"
					},
					{
						"url": "https://debconf17.debconf.org/static/docs/welcome.pdf",
						"title": "Welcome Guide",
						"type": "application/pdf"
					}
				]
			}
		},
		{
			"version": 2017072900,
			"url": "https://programm.froscon.de/2017/schedule.xml",
			"title": "FrOSCon 2017",
			"start": "2017-08-19",
			"end": "2017-08-20",
			"metadata": {
				"icon": "https://ggt.gaa.st/froscon.png",
				"links": [
					{
						"url": "http://www.froscon.org/",
						"title": "Website"
					},
					{
						"url": "https://www.froscon.de/en/news/",
						"title": "News"
					},
					{
						"url": "http://froscon.tv/",
						"title": "Recordings"
					}
				]
			}
		},
		{
			"version": 2017090500,
			"url": "https://cfp.pycon.fr/schedule/xml/",
			"title": "PyConFR 2017",
			"start": "2017-09-21",
			"end": "2017-09-24",
			"metadata": {
				"icon": "https://www.pycon.fr/2017/theme/images/icon2017.png",
				"links": [
					{
						"url": "https://www.pycon.fr/2017/",
						"title": "Site Web"
					},
					{
						"url": "https://www.eventbrite.fr/e/billets-pycon-fr-2017-a-toulouse-37380880219",
						"title": "Inscription"
					},
					{
						"url": "https://www.pycon.fr/2017/pages/venir.html",
						"title": "Venir"
					}
				],
				"rooms": [
					{
						"name": "A.*",
						"latlon": [43.60248, 1.45464]
					},
					{
						"name": "B.*",
						"latlon": [43.60247, 1.45566]
					},
					{
						"name": "C.*",
						"latlon": [43.60214, 1.45462]
					}
				]
			}
		},
		{
			"version": 2017093000,
			"url": "https://www.linuxdays.cz/2017/program/schedule.xml",
			"start": "2017-10-07",
			"end": "2017-10-08",
			"title": "LinuxDays 2017",
			"metadata": {
				"icon": "https://www.linuxdays.cz/2017/obrazky/stopa.png",
				"links": [
					{
						"title": "Website",
						"url": "https://www.linuxdays.cz/2017/"
					},
					{
						"title": "Map",
						"type": "image/png",
						"url": "https://www.linuxdays.cz/2017/obrazky/plan.png"
					}
				],
				"rooms": [
					{
						"latlon": [50.105249, 14.390095],
						"name": "105"
					},
					{
						"latlon": [50.105382, 14.389836],
						"name": "155"
					},
					{
						"latlon": [50.105138, 14.390298],
						"name": "107"
					},
					{
						"latlon": [50.105047, 14.390432],
						"name": "111"
					}
				]
			}
		},
		{
			"version": 2017100700,
			"url": "https://vcfb.de/2017/schedule.xml",
			"title": "Vintage Computing Festival Berlin 2017",
			"start": "2017-10-07",
			"end": "2017-10-08",
			"metadata": {
				"links": [
					{
						"url": "https://vcfb.de/2017/index.html.en",
						"title": "Website"
					},
					{
						"url": "http://vcfb.de/2017/images/raumplan_bunt_2017_rotiert_en.png",
						"title": "Map",
						"type": "image/png"
					}
				]
			}
		},
		{
			"version": 2017100800,
			"url": "https://fahrplan.privacyweek.at/schedule.xml",
			"title": "PrivacyWeek 2017",
			"start": "2017-10-23",
			"end": "2017-10-29",
			"metadata": {
				"icon": "https://privacyweek.at/icon-256x256.png",
				"links": [
					{
						"url": "https://privacyweek.at/",
						"title": "Website"
					}
				]
			}
		},
		{
			"version": 2017101700,
			"url": "https://frab.fscons.org/en/fscons17/public/schedule.xml",
			"title": "FSCONS 2017",
			"start": "2017-11-04",
			"end": "2017-11-05",
			"metadata": {
				"links": [
					{
						"url": "https://fscons.org/2017/",
						"title": "Website"
					},
					{
						"url": "https://fscons.org/2017/news.html",
						"title": "News"
					},
					{
						"url": "https://www.youtube.com/user/FSCONSTalks",
						"title": "Recordings"
					}
				]
			}
		},
		{
			"version": 2017101800,
			"url": "https://participez-2017.capitoledulibre.org/schedule/xml/",
			"title": "Capitole du Libre 2017",
			"start": "2017-11-18",
			"end": "2017-11-19",
			"metadata": {
				"links": [
					{
						"url": "https://2017.capitoledulibre.org/",
						"title": "Site web"
					}
				],
				"rooms": [
					{
						"name": "A.*",
						"latlon": [43.60248, 1.45464]
					},
					{
						"name": "B.*",
						"latlon": [43.60247, 1.45566]
					},
					{
						"name": "C.*",
						"latlon": [43.60214, 1.45462]
					},
					{
						"name": "Foyer.*",
						"latlon": [43.60207, 1.45591]
					}
				]
			}
		},
		{
			"version": 2017100900,
			"url": "https://afup.org/event/forumphp2017/planning.ics",
			"title": "Forum PHP 2017",
			"id": "Forum PHP 2017",
			"start": "2017-10-26",
			"end": "2017-10-27",
			"metadata": {
				"links": [
					{
						"url": "https://event.afup.org/",
						"title": "Site Web"
					},
					{
						"url": "https://afup.org/event/forumphp2017/tickets",
						"title": "Tarifs et inscription"
					}
				]
			}
		},
		{
			"version": 2017102000,
			"url": "https://conf-ng.jres.org/2017/rest/planning.ics",
			"id": "JRES 2017",
			"title": "JRES 2017",
			"start": "2017-11-14",
			"end": "2017-11-17",
			"metadata": {
				"links": [
					{
						"url": "https://www.jres.org/fr",
						"title": "Site Web"
					},
					{
						"url": "https://www.jres.org/fr/inscription-aux-jres-2017",
						"title": "Inscription"
					}
				]
			}
		},
		{
			"version": 2017111300,
			"url": "https://www.linuxday.at/vortraege/2017/calendar.ics",
			"title": "LinuxDay.at 2017",
			"id": "LinuxDay.at Vortraege",
			"start": "2017-12-02",
			"end": "2017-12-02",
			"metadata": {
				"links": [
					{
						"url": "https://www.linuxday.at/",
						"title": "Webseite"
					},
					{
						"url": "https://www.linuxday.at/standplan-2017",
						"title": "Standplan"
					},
					{
						"url": "https://www.linuxday.at/aussteller/2017",
						"title": "Aussteller"
					},
					{
						"url": "https://www.linuxday.at/workshops/2017",
						"title": "Workshops"
					}
				]
			}
		},
		{
			"version": 2017111000,
			"url": "https://nluug.nl/events/nj17/20171116-schedule.xml",
			"title": "NLUUG Autumn 2017",
			"start": "2017-11-16",
			"end": "2017-11-16",
			"metadata": {
				"icon": "https://nluug.nl/events/nj17/nluug-icon-300.png",
				"links": [
					{
						"url": "https://www.nluug.nl/index.html",
						"title": "NLUUG Website"
					},
					{
						"url": "https://www.nluug.nl/events/nj17/programma.html",
						"title": "Conference Program (website)"
					}
				]
			}
		},
		{
			"version": 2017111300,
			"url": "https://botconf2017.sched.com/all.ics",
			"id": "botconf2017",
			"title": "Botconf 2017",
			"start": "2017-12-06",
			"end": "2017-12-08",
			"metadata": {
				"links": [
					{
						"url": "https://www.botconf.eu/botconf-2017/",
						"title": "Website"
					},
					{
						"url": "https://www.botconf.eu/botconf-2017/register-for-botconf-2017/",
						"title": "Registration"
					}
				]
			}
		},
		{
			"title": "34th Chaos Communication Congress",
			"metadata": {
				"links": [
					{
						"url": "https://events.ccc.de/congress/2017/wiki/index.php/Main_Page",
						"title": "Wiki"
					},
					{
						"title": "Weblog",
						"url": "https://events.ccc.de/"
					}
				]
			},
			"url": "https://fahrplan.events.ccc.de/congress/2017/Fahrplan/schedule.xml",
			"start": "2017-12-26",
			"end": "2017-12-30",
			"version": 2017121700
		},
		{
			"version": 2018020200,
			"url": "https://fosdem.org/2018/schedule/xml",
			"title": "FOSDEM 2018",
			"start": "2018-02-03",
			"end": "2018-02-04",
			"metadata": {
				"fosdemRoomStatus": "https://api.fosdem.org/roomstatus/v1/listrooms",
				"links": [
					{
						"url": "https://fosdem.org/2018/",
						"title": "Website"
					},
					{
						"url": "https://fosdem.org/2018/assets/booklet_general-ca5afc2e63511de952229ade11cfd63117f2378208e1cc930c645fbd300c9b9f.pdf",
						"title": "Info booklet",
						"type": "application/pdf"
					},
					{
						"url": "https://fosdem.org/2018/assets/campusmap-5f4dd1f191a8e9ac948735dbd168705d99376da74d320bc2bbe2549173af3e51.png",
						"title": "Map",
						"type": "image/png"
					},
					{
						"url": "https://fosdem.org/2018/stands/",
						"title": "Stands"
					}
				],
				"icon": "https://fosdem.org/2018/assets/style/logo-gear-7204a6874eb0128932db10ff4030910401ac06f4e907f8b4a40da24ba592b252.png",
				"rooms": [
					{
						"name": "Janson",
						"latlon": [50.813231, 4.3791498]
					},
					{
						"name": "K\\..*",
						"show_name": "K building",
						"latlon": [50.8146969, 4.3817676]
					},
					{
						"name": "H\\..*",
						"show_name": "H.*",
						"latlon": [50.8127773, 4.3799053]
					},
					{
						"name": "AW.*",
						"show_name": "AW building",
						"latlon": [50.812139, 4.380602]
					},
					{
						"name": "UA.*",
						"show_name": "UA wing",
						"latlon": [50.811683, 4.3826425]
					},
					{
						"name": "UB.*",
						"show_name": "UB wing",
						"latlon": [50.8120565, 4.382176]
					},
					{
						"name": "UD.*",
						"show_name": "UD wing",
						"latlon": [50.812691, 4.3818835]
					}
				]
			}
		},
		{
			"start": "2018-01-22",
			"end": "2018-01-26",
			"version": 2018011900,
			"url": "https://linux.conf.au/schedule/conference.ics",
			"title": "linux.conf.au 2018",
			"metadata": {
				"links": [
					{
						"url": "https://linux.conf.au/",
						"title": "Website"
					},
					{
						"url": "https://wiki.linux.conf.au/wiki/Main_Page",
						"title": "Wiki"
					}
				]
			}
		},
		{
			"version": 2018031100,
			"url": "http://ical.jdll.org/",
			"title": "JDLL 2018",
			"start": "2018-03-24",
			"end": "2018-03-25",
			"metadata": {
				"links": [
					{
						"url": "http://www.jdll.org/",
						"title": "Site web"
					},
					{
						"url": "http://www.jdll.org/pratique/plan/",
						"title": "Plan"
					}
				]
			}
		},
		{
			"start": "2018-03-22",
			"end": "2018-03-25",
			"version": 2018030900,
			"url": "https://raw.githubusercontent.com/heysadboy/open-event-apps/master/samples/FOSSASIA%20Summit.ics",
			"id": "FOSSASIA 2018",
			"title": "FOSSASIA 2018",
			"metadata": {
				"links": [
					{
						"url": "https://2018.fossasia.org/",
						"title": "Website"
					},
					{
						"url": "https://2018.fossasia.org/event/schedule.html",
						"title": "Online schedule"
					},
					{
						"url": "https://2018.fossasia.org/tickets/",
						"title": "Tickets"
					}
				]
			}
		},
		{
			"start" : "2018-03-24",
			"end" : "2018-03-25",
			"version" : 2018032000,
			"url" : "https://libreplanet.org/2018/schedule.ics",
			"id" : "LibrePlanet 2018",
			"title" : "LibrePlanet 2018",
			"metadata" : {
				"icon" : "https://libreplanet.org/2018/assets/img/site_logo_alternate-small.png",
				"links" : [
					{
						"url" : "https://libreplanet.org/2018/",
						"title" : "Website"
					},
					{
						"url" : "https://www.libreplanet.org/2018/live",
						"title" : "Livestream"
					}
				],
				"rooms": [
					{
						"name": "Workshop.*|.*26-.*",
						"latlon": [42.36100, -71.09054]
					},
					{
						"name": ".*31-.*",
						"latlon": [42.36043, -71.09275]
					},
					{
						"name": ".*32-.*",
						"latlon": [42.36159, -71.09045]
					},
					{
						"name": ".*34-.*",
						"latlon": [42.36111, -71.09194]
					}
				]
			}
		},
		{
			"version": 2018050301,
			"url": "https://nluug.nl/events/vj18/schedule.xml",
			"title": "NLUUG Spring 2018",
			"start": "2018-05-15",
			"end": "2018-05-15",
			"metadata": {
				"icon": "https://nluug.nl/events/vj18/nluug-icon-300.png",
				"links": [
					{
						"url": "https://www.nluug.nl/index.html",
						"title": "NLUUG Website"
					},
					{
						"url": "https://www.nluug.nl/events/vj18/programma.html",
						"title": "Conference Program (website)"
					}
				],
				"rooms": [
					{
						"name": "Room 1",
						"latlon": [52.060788, 5.108085]
					},
					{
						"name": "Room 2"
						"latlon": [52.060788, 5.108085]
					},
					{
						"name": "Room 3"
						"latlon": [52.060788, 5.108085]
					}
				]
			}
		}
	]
}
